pulsemaker/PulseDesigner.py
pulsemaker/ScheduleDesigner.py
pulsemaker/__init__.py
pulsemaker/_version.py
pulsemaker-0.2.0b0.dist-info/LICENSE
pulsemaker-0.2.0b0.dist-info/METADATA
pulsemaker-0.2.0b0.dist-info/WHEEL
pulsemaker-0.2.0b0.dist-info/top_level.txt
pulsemaker-0.2.0b0.dist-info/RECORD
